dj_payfast-0.1.10.dist-info/licenses/LICENSE
payfast/__init__.py
payfast/admin.py
payfast/apps.py
payfast/conf.py
payfast/exceptions.py
payfast/forms.py
payfast/pagination.py
payfast/signals.py
payfast/urls.py
payfast/utils.py
payfast/migrations/0001_initial.py
payfast/migrations/0002_payfastpayment_signature.py
payfast/migrations/0003_alter_payfastpayment_m_payment_id_and_more.py
payfast/migrations/__init__.py
payfast/models/__init__.py
payfast/models/once_off_payments.py
payfast/models/recurring_payments.py
payfast/serializers/__init__.py
payfast/serializers/normal_payments.py
payfast/static/admin/css/custom_admin.css
payfast/templates/payfast/checkout.html
payfast/templates/payfast/payment_cancel.html
payfast/templates/payfast/payment_form.html
payfast/templates/payfast/payment_success.html
payfast/views/__init__.py
payfast/views/normal_payment_views.py
payfast/views/recurring_payment_views.py
dj_payfast-0.1.10.dist-info/METADATA
dj_payfast-0.1.10.dist-info/WHEEL
dj_payfast-0.1.10.dist-info/top_level.txt
dj_payfast-0.1.10.dist-info/RECORD
